rockpool/__init__.py
rockpool/analysis.py
rockpool/parameters.py
rockpool/timeseries.py
rockpool/version.py
rockpool/devices/__init__.py
rockpool/devices/dynapse/NeuronNeuronConnector.py
rockpool/devices/dynapse/__init__.py
rockpool/devices/dynapse/dynap_hw.py
rockpool/devices/dynapse/dynapse_control.py
rockpool/devices/dynapse/dynapse_control_extd.py
rockpool/devices/dynapse/params.py
rockpool/devices/dynapse/rpyc_headless.py
rockpool/devices/dynapse/server.py
rockpool/devices/dynapse/tools.py
rockpool/devices/dynapse/virtual_dynapse.py
rockpool/nn/__init__.py
rockpool/nn/combinators/__init__.py
rockpool/nn/combinators/ffwd_stack.py
rockpool/nn/combinators/sequential.py
rockpool/nn/layers/__init__.py
rockpool/nn/layers/aeif_nest.py
rockpool/nn/layers/event_pass.py
rockpool/nn/layers/exp_synapses_brian.py
rockpool/nn/layers/exp_synapses_manual.py
rockpool/nn/layers/filter_bank.py
rockpool/nn/layers/iaf_brian.py
rockpool/nn/layers/iaf_cl.py
rockpool/nn/layers/iaf_digital.py
rockpool/nn/layers/iaf_nest.py
rockpool/nn/layers/layer.py
rockpool/nn/layers/rate.py
rockpool/nn/layers/spike_ads.py
rockpool/nn/layers/spike_bt.py
rockpool/nn/layers/updown.py
rockpool/nn/modules/__init__.py
rockpool/nn/modules/module.py
rockpool/nn/modules/timed_module.py
rockpool/nn/modules/brian/__init__.py
rockpool/nn/modules/dynapse/__init__.py
rockpool/nn/modules/jax/__init__.py
rockpool/nn/modules/jax/jax_module.py
rockpool/nn/modules/jax/lif_jax.py
rockpool/nn/modules/jax/rate_jax.py
rockpool/nn/modules/native/__init__.py
rockpool/nn/modules/native/analogFrontEnd.py
rockpool/nn/modules/native/instant.py
rockpool/nn/modules/native/linear.py
rockpool/nn/modules/nest/__init__.py
rockpool/nn/modules/nest/iaf_nest.py
rockpool/nn/modules/torch/__init__.py
rockpool/nn/modules/torch/lif_torch.py
rockpool/nn/modules/torch/torch_module.py
rockpool/nn/networks/__init__.py
rockpool/nn/networks/net_ads.py
rockpool/nn/networks/net_deneve.py
rockpool/training/__init__.py
rockpool/training/jax_debug.py
rockpool-2.0.dist-info/LICENSE
rockpool-2.0.dist-info/METADATA
rockpool-2.0.dist-info/WHEEL
rockpool-2.0.dist-info/top_level.txt
rockpool-2.0.dist-info/RECORD
