Metadata-Version: 2.1
Name: rockpool
Version: 2.0
Summary: A Python package for developing, simulating and training spiking neural networks, and deploying on neuromorphic hardware
Home-page: UNKNOWN
Author: SynSense
Author-email: dylan.muir@synsense.ai
License: UNKNOWN
Project-URL: Source Code, https://gitlab.com/SynSense/rockpool
Project-URL: Documentation, https://rockpool.ai
Project-URL: Bug Tracker, https://gitlab.com/SynSense/rockpool/-/issues
Keywords: spiking neural network SNN neuromorphic
Platform: UNKNOWN
Classifier: Development Status :: 4 - Beta
Classifier: Programming Language :: Python :: 3
Classifier: License :: OSI Approved :: GNU Affero General Public License v3 or later (AGPLv3+)
Requires-Python: >=3.6
Requires-Dist: numpy
Provides-Extra: all
Requires-Dist: tqdm ; extra == 'all'
Requires-Dist: brian2 ; extra == 'all'
Requires-Dist: pytest (>=6.0) ; extra == 'all'
Requires-Dist: pytest-xdist ; extra == 'all'
Requires-Dist: torch ; extra == 'all'
Requires-Dist: torchvision ; extra == 'all'
Requires-Dist: rpyc ; extra == 'all'
Requires-Dist: jax ; extra == 'all'
Requires-Dist: jaxlib ; extra == 'all'
Requires-Dist: sphinx ; extra == 'all'
Requires-Dist: nbsphinx ; extra == 'all'
Requires-Dist: sphinx-autobuild ; extra == 'all'
Requires-Dist: sphinx-rtd-theme ; extra == 'all'
Requires-Dist: recommonmark ; extra == 'all'
Requires-Dist: pandoc ; extra == 'all'
